loapy/__init__.py
loapy/errors.py
loapy/http.py
loapy/py.typed
loapy/types/armories.py
loapy/types/auctions.py
loapy/types/basic.py
loapy/types/characters.py
loapy/types/gamecontents.py
loapy/types/guilds.py
loapy/types/markets.py
loapy/types/news.py
loapy-3.0.0.0.dist-info/LICENSE
loapy-3.0.0.0.dist-info/METADATA
loapy-3.0.0.0.dist-info/WHEEL
loapy-3.0.0.0.dist-info/RECORD
