Metadata-Version: 2.1
Name: loapy
Version: 3.0.0.0
Summary: An unofficial asynchronous SDK for Lostark Open API written in Python.
Home-page: https://github.com/korlark/loapy
License: MIT
Author: Mary
Author-email: mareowst@gmail.com
Requires-Python: >=3.7,<4.0
Classifier: License :: OSI Approved :: MIT License
Classifier: Programming Language :: Python :: 3
Classifier: Programming Language :: Python :: 3.7
Classifier: Programming Language :: Python :: 3.8
Classifier: Programming Language :: Python :: 3.9
Classifier: Programming Language :: Python :: 3.10
Classifier: Programming Language :: Python :: 3.11
Requires-Dist: aiohttp (>=3.7.4,<4.0.0)
Requires-Dist: typing-extensions (>=4.4.0,<5.0.0)
Requires-Dist: ujson (>=5.7.0,<6.0.0)
Project-URL: Repository, https://github.com/korlark/loapy
